google/fhir/__init__.py
google/fhir/_primitive_time_utils.py
google/fhir/codes.py
google/fhir/extensions.py
google/fhir/extensions_test.py
google/fhir/fhir_errors.py
google/fhir/fhir_errors_test.py
google/fhir/primitive_handler.py
google/fhir/primitive_handler_test.py
google/fhir/py.typed
google/fhir/references.py
google/fhir/resource_validation.py
google/fhir/json_format/__init__.py
google/fhir/json_format/_json_parser.py
google/fhir/json_format/_json_printer.py
google/fhir/json_format/json_format_primitives_test.py
google/fhir/json_format/json_format_test.py
google/fhir/json_format/wrappers/__init__.py
google/fhir/json_format/wrappers/_base64_binary.py
google/fhir/json_format/wrappers/_date.py
google/fhir/json_format/wrappers/_date_time.py
google/fhir/json_format/wrappers/_decimal.py
google/fhir/json_format/wrappers/_instant.py
google/fhir/json_format/wrappers/_primitive_wrappers.py
google/fhir/json_format/wrappers/_time.py
google/fhir/r4/__init__.py
google/fhir/r4/codes_test.py
google/fhir/r4/extensions_test.py
google/fhir/r4/json_format.py
google/fhir/r4/json_format_test.py
google/fhir/r4/primitive_handler.py
google/fhir/r4/primitive_handler_test.py
google/fhir/r4/references_test.py
google/fhir/r4/resource_validation.py
google/fhir/r4/resource_validation_test.py
google/fhir/stu3/__init__.py
google/fhir/stu3/codes_test.py
google/fhir/stu3/extensions_test.py
google/fhir/stu3/json_format.py
google/fhir/stu3/json_format_test.py
google/fhir/stu3/primitive_handler.py
google/fhir/stu3/primitive_handler_test.py
google/fhir/stu3/references_test.py
google/fhir/stu3/resource_validation.py
google/fhir/stu3/resource_validation_test.py
google/fhir/testing/__init__.py
google/fhir/testing/protobuf_compare.py
google/fhir/testing/testdata_utils.py
google/fhir/utils/__init__.py
google/fhir/utils/annotation_utils.py
google/fhir/utils/annotation_utils_test.py
google/fhir/utils/fhir_package.py
google/fhir/utils/fhir_package_test.py
google/fhir/utils/fhir_types.py
google_fhir-0.7.3.dist-info/METADATA
google_fhir-0.7.3.dist-info/WHEEL
google_fhir-0.7.3.dist-info/top_level.txt
google_fhir-0.7.3.dist-info/RECORD
