Metadata-Version: 2.1
Name: google-fhir
Version: 0.7.3
Summary: Tools for parsing and printing FHIR JSON.
Home-page: https://github.com/google/fhir
Author: Google LLC
Author-email: google-fhir-pypi@google.com
License: Apache 2.0
Download-URL: https://github.com/google/fhir/releases
Keywords: google fhir python healthcare
Platform: UNKNOWN
Classifier: License :: OSI Approved :: Apache Software License
Classifier: Operating System :: MacOS :: MacOS X
Classifier: Operating System :: POSIX :: Linux
Classifier: Programming Language :: Python :: 3.6
Classifier: Programming Language :: Python :: 3.7
Classifier: Programming Language :: Python :: 3.8
Classifier: Programming Language :: Python :: 3.9
Requires-Python: >=3.6, <3.10
Requires-Dist: absl-py (~=0.10.0)
Requires-Dist: protobuf (~=3.13)
Requires-Dist: python-dateutil (~=2.8)
Requires-Dist: backports.zoneinfo (~=0.2.1) ; python_version < "3.9"
